{
    "fpd_attempts_observed": {
        "n_of_results": 937,
        "sum": {
            "BrowserProperties": 307226,
            "AlgorithmicMethods": 216381,
            "CrawlFpInspector": 7460
        },
        "average": {
            "BrowserProperties": 327.88260405549624,
            "AlgorithmicMethods": 230.92956243329775,
            "CrawlFpInspector": 7.9615795090715045
        }
    },
    "fpd_attempts_blocked_directly": {
        "n_of_results": 937,
        "sum": {},
        "average": {}
    },
    "fpd_attempts_blocked_transitively": {
        "n_of_results": 937,
        "sum": {},
        "average": {}
    },
    "fpd_attempts_blocked_in_total": {
        "n_of_results": 937,
        "sum": {},
        "average": {}
    },
    "requests_observed": {
        "n_of_results": 937,
        "sum": 100525,
        "average": 107.28388473852722
    },
    "requests_blocked_directly": {
        "n_of_results": 937,
        "sum": 0,
        "average": 0.0
    },
    "requests_blocked_in_total": {
        "n_of_results": 937,
        "sum": 0,
        "average": 0.0
    },
    "requests_blocked_transitively": {
        "n_of_results": 937,
        "sum": 0,
        "average": 0.0
    },
    "requests_blocked_that_have_child_requests": {
        "n_of_results": 937,
        "sum": 0,
        "average": 0.0
    },
    "average_request_block_level": {
        "n_of_results": 0,
        "sum": 0,
        "average": 0
    },
    "blocked_subtrees_data": {
        "n_of_results": 937,
        "sum": {
            "subtrees_fully_blocked": 0,
            "subtrees_partially_blocked": 0,
            "subtrees_not_blocked": 60617,
            "subtrees_in_total": 60617,
            "trees_with_blocked_root_node": 0
        },
        "average": {
            "subtrees_fully_blocked": 0.0,
            "subtrees_partially_blocked": 0.0,
            "subtrees_not_blocked": 64.69263607257204,
            "subtrees_in_total": 64.69263607257204,
            "trees_with_blocked_root_node": 0.0
        }
    }
}